mytoolset/__init__.py
mytoolset/uninstall.py
mytoolset-0.0.3.dist-info/LICENSE
mytoolset-0.0.3.dist-info/METADATA
mytoolset-0.0.3.dist-info/WHEEL
mytoolset-0.0.3.dist-info/top_level.txt
mytoolset-0.0.3.dist-info/RECORD
